sanic_envconfig/__init__.py
sanic_envconfig/envconfig.py
sanic_envconfig/utils.py
sanic_envconfig-1.3.4.dist-info/LICENCE.txt
sanic_envconfig-1.3.4.dist-info/METADATA
sanic_envconfig-1.3.4.dist-info/WHEEL
sanic_envconfig-1.3.4.dist-info/top_level.txt
sanic_envconfig-1.3.4.dist-info/RECORD
